requirements_docs.txt
requirements_lint.txt
requirements_test.txt
requirements_typing.txt
perun/__init__.py
perun/cli.py
perun/check/__init__.py
perun/check/average_amount_threshold.py
perun/check/best_model_order_equality.py
perun/check/exclusive_time_outliers.py
perun/check/factory.py
perun/check/fast_check.py
perun/check/general_detection.py
perun/check/integral_comparison.py
perun/check/linear_regression.py
perun/check/local_statistics.py
perun/check/nonparam_helpers.py
perun/check/polynomial_regression.py
perun/cli_groups/__init__.py
perun/cli_groups/check_cli.py
perun/cli_groups/config_cli.py
perun/cli_groups/run_cli.py
perun/cli_groups/utils_cli.py
perun/collect/__init__.py
perun/collect/bounds/__init__.py
perun/collect/bounds/parser.py
perun/collect/bounds/run.py
perun/collect/bounds/bin/clang-3.5
perun/collect/bounds/bin/libLLVM-3.5.so.1
perun/collect/bounds/bin/libffi.so.6
perun/collect/bounds/bin/libtinfo.so.5
perun/collect/bounds/bin/libz3.so
perun/collect/bounds/bin/loopus
perun/collect/bounds/bin/include/Intrin.h
perun/collect/bounds/bin/include/__wmmintrin_aes.h
perun/collect/bounds/bin/include/__wmmintrin_pclmul.h
perun/collect/bounds/bin/include/altivec.h
perun/collect/bounds/bin/include/ammintrin.h
perun/collect/bounds/bin/include/arm_acle.h
perun/collect/bounds/bin/include/arm_neon.h
perun/collect/bounds/bin/include/avx2intrin.h
perun/collect/bounds/bin/include/avxintrin.h
perun/collect/bounds/bin/include/bmi2intrin.h
perun/collect/bounds/bin/include/bmiintrin.h
perun/collect/bounds/bin/include/cpuid.h
perun/collect/bounds/bin/include/emmintrin.h
perun/collect/bounds/bin/include/f16cintrin.h
perun/collect/bounds/bin/include/float.h
perun/collect/bounds/bin/include/fma4intrin.h
perun/collect/bounds/bin/include/fmaintrin.h
perun/collect/bounds/bin/include/ia32intrin.h
perun/collect/bounds/bin/include/immintrin.h
perun/collect/bounds/bin/include/iso646.h
perun/collect/bounds/bin/include/limits.h
perun/collect/bounds/bin/include/lzcntintrin.h
perun_toolsuite-0.21.8.dist-info/AUTHORS.rst
perun_toolsuite-0.21.8.dist-info/LICENSE
perun_toolsuite-0.21.8.dist-info/METADATA
perun_toolsuite-0.21.8.dist-info/WHEEL
perun_toolsuite-0.21.8.dist-info/entry_points.txt
perun_toolsuite-0.21.8.dist-info/top_level.txt
perun_toolsuite-0.21.8.dist-info/RECORD
