Metadata-Version: 2.1
Name: perun-toolsuite
Version: 0.21.8
Summary: Perun: Lightweight Performance Version System
Author: Matus Liscinsky, Peter Mocary, Ondrej Michal, Vojtech Hajek, Vladimir Hucovic
Author-email: Tomas Fiedor <TomasFiedor@gmail.com>, Jiri Pavela <Jirka.Pavela@gmail.com>, Radim Podola <rpodola@gmail.com>, Simon Stupinsky <simondestupinsky@gmail.com>
License: GNU GENERAL PUBLIC LICENSE
Project-URL: Repository, https://github.com/Perfexionists/perun.git
Project-URL: Demonstration, https://www.fit.vutbr.cz/research/groups/verifit/tools/perun-demo/
Project-URL: Changelog, https://github.com/Perfexionists/perun/blob/master/CHANGELOG.rst
Requires-Python: >=3.9
License-File: LICENSE
License-File: AUTHORS.rst
Requires-Dist: click >=8.1
Requires-Dist: GitPython >=3.1.30
Requires-Dist: gitdb >=4.0.10
Requires-Dist: Faker >=19.3
Requires-Dist: ruamel.yaml >=0.17
Requires-Dist: Jinja2 >=3.1
Requires-Dist: python-magic >=0.4
Requires-Dist: angr >=9.2
Requires-Dist: numpy >=1.24
Requires-Dist: pandas >=2.0
Requires-Dist: statsmodels >=0.14
Requires-Dist: scikit-learn >=1.3
Requires-Dist: scipy >=1.10
Requires-Dist: networkx >=3.1
Requires-Dist: bokeh >=3.1
Requires-Dist: matplotlib >=3.7
Requires-Dist: termcolor >=2.4
Requires-Dist: tabulate >=0.9
Requires-Dist: holoviews >=1.17
Requires-Dist: kiwisolver !=1.4.5
Provides-Extra: docs
Requires-Dist: Sphinx >=7.1 ; extra == 'docs'
Requires-Dist: sphinx-click >=5.0 ; extra == 'docs'
Provides-Extra: lint
Requires-Dist: pylint >=2.17 ; extra == 'lint'
Provides-Extra: test
Requires-Dist: pytest >=7.4 ; extra == 'test'
Requires-Dist: pytest-cov >=4.1 ; extra == 'test'
Requires-Dist: tox >=4.9.0 ; extra == 'test'
Provides-Extra: typing
Requires-Dist: mypy >=1.5 ; extra == 'typing'
Requires-Dist: mypy-extensions >=1.0 ; extra == 'typing'
Requires-Dist: typing-extensions >=4.7 ; extra == 'typing'
Requires-Dist: types-tabulate >=0.9 ; extra == 'typing'
Requires-Dist: types-setuptools >=68.1.0.0 ; extra == 'typing'
Requires-Dist: pandas-stubs >=2.0 ; extra == 'typing'
Requires-Dist: nptyping >=2.5.0 ; extra == 'typing'
